Metadata-Version: 2.1
Name: astrotitles
Version: 0.1.3
Summary: Automatically generate subtitles using the Astrotitles command line interface.
Home-page: https://github.com/Astrotitles/cli
Download-URL: https://github.com/Astrotitles/cli.git
Author: Ben Webster
License: AGPL-3.0
Keywords: AI,Whisper AI,Subtitles
License-File: LICENCE.txt
